<annotation>
	<folder>轉檔</folder>
	<filename>100_20200608_171956.png</filename>
	<path>E:\windows_v1.8.0\轉檔\100_20200608_171956.png</path>
	<source>
		<database>Unknown</database>
	</source>
	<size>
		<width>2268</width>
		<height>3024</height>
		<depth>3</depth>
	</size>
	<segmented>0</segmented>
	<object>
		<name>Paper</name>
		<pose>Unspecified</pose>
		<truncated>0</truncated>
		<difficult>0</difficult>
		<bndbox>
			<xmin>216</xmin>
			<ymin>367</ymin>
			<xmax>1416</xmax>
			<ymax>1996</ymax>
		</bndbox>
	</object>
</annotation>
